README.md
setup.cfg
setup.py
testlinkwrapper/__init__.py
testlinkwrapper.egg-info/PKG-INFO
testlinkwrapper.egg-info/SOURCES.txt
testlinkwrapper.egg-info/dependency_links.txt
testlinkwrapper.egg-info/requires.txt
testlinkwrapper.egg-info/top_level.txt