Metadata-Version: 2.1
Name: testlinkwrapper
Version: 0.1.8
Summary: Wrapper for test tool Testlink
Home-page: https://github.com/Manzanero/testlinkwrapper
Author: Alejandro Manzanero
Author-email: alejmans@domain.com
License: MIT
Download-URL: https://github.com/Manzanero/testlinkwrapper/archive/v_0_1_8.tar.gz
Keywords: test,testlink,wrapper
Platform: UNKNOWN
Classifier: Development Status :: 4 - Beta
Classifier: Intended Audience :: Developers
Classifier: Topic :: Software Development :: Build Tools
Classifier: License :: OSI Approved :: MIT License
Classifier: Programming Language :: Python :: 3.8
